tadqeeq/__init__.py
tadqeeq/cli.py
tadqeeq/draft.py
tadqeeq/implementations.py
tadqeeq/utils.py
tadqeeq/widgets.py
tadqeeq-1.12.0.dist-info/licenses/LICENSE
tadqeeq-1.12.0.dist-info/METADATA
tadqeeq-1.12.0.dist-info/WHEEL
tadqeeq-1.12.0.dist-info/entry_points.txt
tadqeeq-1.12.0.dist-info/top_level.txt
tadqeeq-1.12.0.dist-info/RECORD
