Metadata-Version: 2.4
Name: tadqeeq
Version: 1.12.0
Summary: An interactive PyQt5 image annotation tool for segmentation masks and bounding boxes.
Home-page: https://github.com/orbits-it/tadqeeq
Author: Mohamed Behery
Author-email: mohamed.i.behery@proton.me
Classifier: Programming Language :: Python :: 3.11
Classifier: License :: OSI Approved :: MIT License
Classifier: Operating System :: OS Independent
Classifier: Intended Audience :: Developers
Classifier: Topic :: Software Development :: Libraries :: Python Modules
Classifier: Topic :: Scientific/Engineering :: Artificial Intelligence
Classifier: Topic :: Scientific/Engineering :: Image Recognition
Requires-Python: >=3.8
License-File: LICENSE
Requires-Dist: imageio==2.37.0
Requires-Dist: lazy_loader==0.4
Requires-Dist: networkx==3.4.2
Requires-Dist: numpy==2.2.5
Requires-Dist: packaging==25.0
Requires-Dist: pillow==11.2.1
Requires-Dist: PyQt5<6.0,>=5.15.0
Requires-Dist: PyQt5-Qt5<6.0,>=5.15.0
Requires-Dist: PyQt5_sip<13.0,>=12.17
Requires-Dist: scikit-image==0.25.2
Requires-Dist: scipy==1.15.2
Requires-Dist: tifffile==2025.3.30
Provides-Extra: dev
Requires-Dist: build; extra == "dev"
Requires-Dist: twine; extra == "dev"
Requires-Dist: wheel; extra == "dev"
Dynamic: author
Dynamic: author-email
Dynamic: classifier
Dynamic: description
Dynamic: description-content-type
Dynamic: home-page
Dynamic: license-file
Dynamic: provides-extra
Dynamic: requires-dist
Dynamic: requires-python
Dynamic: summary
